archive/part2/build_flash_attn_amd.sh
archive/part2/build_flash_attn_amd_outline.sh
archive/part2/build_flash_attn_amd_part1.sh
archive/part2/build_flash_attn_amd_part2.sh
archive/part2/build_flash_attn_amd_part3.sh
archive/part2/build_onnxruntime.sh
archive/part2/build_onnxruntime_part1.sh
archive/part2/build_onnxruntime_part2.sh
archive/part2/build_onnxruntime_part3.sh
archive/part4/custom_verify_installation.sh
archive/part4/enhanced_verify_installation.sh
archive/part4/test_comprehensive_integration.sh
archive/part4/test_config_integration.sh
archive/part4/test_dependency_conflicts.sh
archive/part4/test_env_consistency.sh
archive/part4/test_error_recovery.sh
archive/part4/test_installation_order.sh
archive/part4/test_package_manager_integration.sh
archive/part4/test_rocm_detection.sh
archive/part4/test_venv_compatibility.sh
archive/part7/install_ml_stack_outline.sh
archive/part9/onnxruntime_rocm_venv/bin/activate_this.py
archive/part9/pytorch_rocm_venv/bin/activate_this.py
assets/ml_stack_logo.png
assets/ml_stack_logo_ascii.txt
benchmarks/analyze_flash_attn_results.py
benchmarks/benchmark_flash_attn_amd.py
benchmarks/flash_attention_benchmark.py
benchmarks/matrix_multiplication_benchmark.py
benchmarks/memory_bandwidth_benchmark.py
benchmarks/pytorch_gpu_benchmark.py
benchmarks/transformer_benchmark.py
core/flash_attention/__init__.py
core/flash_attention/flash_attention_amd.py
core/flash_attention/setup_flash_attn_amd.py
core/megatron/amd_adaptation.py
core/megatron/flash_attn_patch.py
core/migraphx/migraphx_wrapper.py
core/migraphx/migraphx_wrapper_full.py
core/migraphx/migraphx_wrapper_simple.py
core/migraphx/setup.py
core/migraphx/migraphx/__init__.py
core/mpi/mpi_distributed.py
core/mpi/mpi_helper.py
core/onnx/onnx_optimizer.py
core/onnx/onnx_utils.py
core/pytorch/pytorch_distributed.py
core/pytorch/pytorch_utils.py
core/rccl/rccl_utils.py
core/rocm/rocm_utils.py
docs/_config.yml
docs/index.md
docs/ml_stack_master_guide.md
stans_ml_stack-0.1.4.dist-info/METADATA
stans_ml_stack-0.1.4.dist-info/WHEEL
stans_ml_stack-0.1.4.dist-info/entry_points.txt
stans_ml_stack-0.1.4.dist-info/top_level.txt
stans_ml_stack-0.1.4.dist-info/RECORD
