Metadata-Version: 2.4
Name: stans-ml-stack
Version: 0.1.4
Summary: A comprehensive machine learning environment optimized for AMD GPUs
Home-page: https://github.com/scooter-lacroix/Stans_MLStack
Author: Stanley Chisango (Scooter Lacroix)
Author-email: "Stanley Chisango (Scooter Lacroix)" <scooterlacroix@gmail.com>
License-Expression: MIT
Project-URL: Homepage, https://github.com/scooter-lacroix/Stans_MLStack
Project-URL: Issues, https://github.com/scooter-lacroix/Stans_MLStack/issues
Project-URL: Documentation, https://github.com/scooter-lacroix/Stans_MLStack/wiki
Classifier: Development Status :: 4 - Beta
Classifier: Intended Audience :: Developers
Classifier: Intended Audience :: Science/Research
Classifier: Programming Language :: Python :: 3
Classifier: Programming Language :: Python :: 3.10
Classifier: Programming Language :: Python :: 3.11
Classifier: Programming Language :: Python :: 3.12
Classifier: Programming Language :: Python :: 3.13
Classifier: Topic :: Scientific/Engineering
Classifier: Topic :: Scientific/Engineering :: Artificial Intelligence
Classifier: Topic :: Software Development :: Libraries :: Python Modules
Requires-Python: >=3.10
Requires-Dist: numpy
Requires-Dist: torch>=2.6.0
Requires-Dist: onnxruntime
Requires-Dist: psutil
Requires-Dist: tqdm
Requires-Dist: requests
Requires-Dist: pyyaml
Dynamic: author
Dynamic: home-page
Dynamic: requires-python
